es_map_writer/__init__.py
es_map_writer/command.py
es_map_writer/queries.py
es_map_writer/scanner.py
es_map_writer/tests.py
es_map_writer/writer.py
es_map_writer-1.0.0a4.dist-info/DESCRIPTION.rst
es_map_writer-1.0.0a4.dist-info/METADATA
es_map_writer-1.0.0a4.dist-info/RECORD
es_map_writer-1.0.0a4.dist-info/WHEEL
es_map_writer-1.0.0a4.dist-info/entry_points.txt
es_map_writer-1.0.0a4.dist-info/metadata.json
es_map_writer-1.0.0a4.dist-info/top_level.txt
